odoo/addons/pos_divide_order_summary/README.rst
odoo/addons/pos_divide_order_summary/__init__.py
odoo/addons/pos_divide_order_summary/__manifest__.py
odoo/addons/pos_divide_order_summary/i18n/it.po
odoo/addons/pos_divide_order_summary/i18n/pos_divide_order_summary.pot
odoo/addons/pos_divide_order_summary/readme/CONTRIBUTORS.md
odoo/addons/pos_divide_order_summary/readme/CREDITS.md
odoo/addons/pos_divide_order_summary/readme/DESCRIPTION.md
odoo/addons/pos_divide_order_summary/static/description/icon.png
odoo/addons/pos_divide_order_summary/static/description/index.html
odoo/addons/pos_divide_order_summary/static/src/xml/pos_divide_order_summary.xml
odoo/addons/pos_divide_order_summary/static/tests/tours/DivideOrderSummary.tour.esm.js
odoo/addons/pos_divide_order_summary/tests/__init__.py
odoo/addons/pos_divide_order_summary/tests/test_frontend.py
odoo_addon_pos_divide_order_summary-18.0.1.0.0.6.dist-info/METADATA
odoo_addon_pos_divide_order_summary-18.0.1.0.0.6.dist-info/WHEEL
odoo_addon_pos_divide_order_summary-18.0.1.0.0.6.dist-info/top_level.txt
odoo_addon_pos_divide_order_summary-18.0.1.0.0.6.dist-info/RECORD
